udemyAPI/UdemyQuestionsAnswers.py
udemyAPI/__init__.py
udemyAPI/playwrightSetup.py
udemyAPI/teachingAssistant.py
udemyAPI/udemyLogin.py
udemyAPI-0.0.1.dist-info/LICENSE
udemyAPI-0.0.1.dist-info/METADATA
udemyAPI-0.0.1.dist-info/WHEEL
udemyAPI-0.0.1.dist-info/top_level.txt
udemyAPI-0.0.1.dist-info/RECORD
