Metadata-Version: 2.1
Name: udemyAPI
Version: 0.0.1
Summary: You can find everything you need in README.MD
Home-page: https://github.com/AzizKpln/udemyAPI
Author: Aziz Kaplan
Author-email: AzizKpln@protonmail.com
License: MIT license
Platform: UNKNOWN
Classifier: Intended Audience :: Developers
Classifier: Topic :: Software Development :: Build Tools
Classifier: License :: OSI Approved :: MIT License
Classifier: Programming Language :: Python :: 3
Classifier: Programming Language :: Python :: 3.7
Classifier: Programming Language :: Python :: 3.8
Classifier: Programming Language :: Python :: 3.9
Classifier: Programming Language :: Python :: 3.10
Classifier: Programming Language :: Python :: 3 :: Only
Requires-Python: >=3.7, <4
License-File: LICENSE
Requires-Dist: playwright
